{"current_index":1,"presets":[{"override_rng":false,"atan_strain":false,"lookahead_length":1,"truncate_effective_angle":false,"variables":[{"identifier":"yaw_facing","visible":true},{"identifier":"yaw_intended","visible":true},{"identifier":"h_spd","visible":true},{"identifier":"v_spd","visible":true},{"identifier":"spd_efficiency","visible":true},{"identifier":"position_x","visible":true},{"identifier":"position_y","visible":true},{"identifier":"position_z","visible":true},{"identifier":"xz_movement","visible":true},{"identifier":"action","visible":true},{"identifier":"rng","visible":true},{"identifier":"moved_dist","visible":true},{"identifier":"atan_basic","visible":true},{"identifier":"atan_start_frame","visible":true}],"framewalk":false,"visualize_objects":false,"atan_start":0,"atan_r":1,"grid_size":35,"reverse_arc":false,"high_magnitude":true,"override_rng_use_index":false,"strain_always":false,"show_effective_angles":true,"swimming_button":"A","track_moved_distance":false,"grind_divisor":8,"moved_distance":0,"atan_d":1,"atan_n":10,"dyaw":false,"override_rng_value":0,"strain_speed_target":false,"strain_left":true,"atan_exp":0,"grid_gap":2,"moved_distance_axis":{"z":0,"y":0,"x":0},"moved_distance_ignore_y":false,"active_style_index":7,"grind":false,"lookahead":false,"goal_angle":0,"format_angles_degrees":false,"swim":true,"ghost_path":"C:\\Users\\austi\\Desktop\\mupen64\\1.1.0\\sm64expert\\sm64lua\\recording.ghost","grind_left":true,"strain_right":false,"format_decimal_points":4,"goal_mag":127,"controller_index":1,"movement_modes":{"match_yaw":2,"reverse_angle":3,"disabled":1,"match_angle":4},"movement_mode":1},{"override_rng":false,"atan_strain":false,"lookahead_length":1,"truncate_effective_angle":false,"variables":[{"visible":true,"identifier":"yaw_facing"},{"visible":true,"identifier":"yaw_intended"},{"visible":true,"identifier":"h_spd"},{"visible":true,"identifier":"v_spd"},{"visible":true,"identifier":"spd_efficiency"},{"visible":true,"identifier":"position_x"},{"visible":true,"identifier":"position_y"},{"visible":true,"identifier":"position_z"},{"visible":true,"identifier":"xz_movement"},{"visible":true,"identifier":"action"},{"visible":true,"identifier":"rng"},{"visible":true,"identifier":"moved_dist"},{"visible":true,"identifier":"atan_basic"},{"visible":true,"identifier":"atan_start_frame"}],"framewalk":false,"visualize_objects":false,"atan_start":0,"grid_gap":2,"grid_size":35,"reverse_arc":false,"high_magnitude":false,"override_rng_use_index":false,"strain_always":false,"show_effective_angles":true,"swimming_button":"A","track_moved_distance":false,"grind_divisor":8,"moved_distance":0,"atan_d":0,"dyaw":false,"moved_distance_axis":{"z":0,"y":0,"x":0},"override_rng_value":0,"strain_speed_target":false,"strain_left":true,"atan_exp":0,"lookahead":false,"atan_r":1,"moved_distance_ignore_y":false,"active_style_index":1,"grind":false,"goal_angle":0,"ghost_path":"C:\\Users\\austi\\Desktop\\mupen64\\1.1.0\\sm64expert\\sm64lua\\recording.ghost","format_angles_degrees":false,"goal_mag":127,"strain_right":false,"grind_left":true,"movement_mode":1,"format_decimal_points":4,"atan_n":10,"controller_index":1,"movement_modes":{"match_yaw":2,"reverse_angle":3,"disabled":1,"match_angle":4},"swim":false},{"override_rng":false,"atan_strain":false,"lookahead_length":1,"truncate_effective_angle":false,"variables":[{"visible":true,"identifier":"yaw_facing"},{"visible":true,"identifier":"yaw_intended"},{"visible":true,"identifier":"h_spd"},{"visible":true,"identifier":"v_spd"},{"visible":true,"identifier":"spd_efficiency"},{"visible":true,"identifier":"position_x"},{"visible":true,"identifier":"position_y"},{"visible":true,"identifier":"position_z"},{"visible":true,"identifier":"xz_movement"},{"visible":true,"identifier":"action"},{"visible":true,"identifier":"rng"},{"visible":true,"identifier":"moved_dist"},{"visible":true,"identifier":"atan_basic"},{"visible":true,"identifier":"atan_start_frame"}],"framewalk":false,"visualize_objects":false,"atan_start":0,"grid_gap":2,"grid_size":35,"reverse_arc":false,"high_magnitude":false,"override_rng_use_index":false,"strain_always":false,"show_effective_angles":true,"swimming_button":"A","track_moved_distance":false,"grind_divisor":8,"moved_distance":0,"atan_d":0,"dyaw":false,"moved_distance_axis":{"z":0,"y":0,"x":0},"override_rng_value":0,"strain_speed_target":false,"strain_left":true,"atan_exp":0,"lookahead":false,"atan_r":1,"moved_distance_ignore_y":false,"active_style_index":1,"grind":false,"goal_angle":0,"ghost_path":"C:\\Users\\austi\\Desktop\\mupen64\\1.1.0\\sm64expert\\sm64lua\\recording.ghost","format_angles_degrees":false,"goal_mag":127,"strain_right":false,"grind_left":true,"movement_mode":1,"format_decimal_points":4,"atan_n":10,"controller_index":1,"movement_modes":{"match_yaw":2,"reverse_angle":3,"disabled":1,"match_angle":4},"swim":false},{"override_rng":false,"atan_strain":false,"lookahead_length":1,"truncate_effective_angle":false,"variables":[{"visible":true,"identifier":"yaw_facing"},{"visible":true,"identifier":"yaw_intended"},{"visible":true,"identifier":"h_spd"},{"visible":true,"identifier":"v_spd"},{"visible":true,"identifier":"spd_efficiency"},{"visible":true,"identifier":"position_x"},{"visible":true,"identifier":"position_y"},{"visible":true,"identifier":"position_z"},{"visible":true,"identifier":"xz_movement"},{"visible":true,"identifier":"action"},{"visible":true,"identifier":"rng"},{"visible":true,"identifier":"moved_dist"},{"visible":true,"identifier":"atan_basic"},{"visible":true,"identifier":"atan_start_frame"}],"framewalk":false,"visualize_objects":false,"atan_start":0,"grid_gap":2,"grid_size":35,"reverse_arc":false,"high_magnitude":false,"override_rng_use_index":false,"strain_always":false,"format_decimal_points":4,"swimming_button":"A","track_moved_distance":false,"grind_divisor":8,"moved_distance":0,"atan_d":0,"strain_right":false,"moved_distance_axis":{"z":0,"y":0,"x":0},"override_rng_value":0,"strain_speed_target":false,"strain_left":true,"atan_exp":0,"goal_mag":127,"atan_r":1,"moved_distance_ignore_y":false,"active_style_index":1,"grind":false,"lookahead":false,"goal_angle":0,"format_angles_degrees":false,"movement_modes":{"match_yaw":2,"reverse_angle":3,"disabled":1,"match_angle":4},"show_effective_angles":true,"grind_left":true,"movement_mode":1,"ghost_path":"C:\\Users\\austi\\Desktop\\mupen64\\1.1.0\\sm64expert\\sm64lua\\recording.ghost","atan_n":10,"controller_index":1,"dyaw":false,"swim":false},{"override_rng":false,"atan_strain":false,"lookahead_length":1,"truncate_effective_angle":false,"variables":[{"visible":true,"identifier":"yaw_facing"},{"visible":true,"identifier":"yaw_intended"},{"visible":true,"identifier":"h_spd"},{"visible":true,"identifier":"v_spd"},{"visible":true,"identifier":"spd_efficiency"},{"visible":true,"identifier":"position_x"},{"visible":true,"identifier":"position_y"},{"visible":true,"identifier":"position_z"},{"visible":true,"identifier":"xz_movement"},{"visible":true,"identifier":"action"},{"visible":true,"identifier":"rng"},{"visible":true,"identifier":"moved_dist"},{"visible":true,"identifier":"atan_basic"},{"visible":true,"identifier":"atan_start_frame"}],"framewalk":false,"visualize_objects":false,"atan_start":0,"grid_gap":2,"grid_size":35,"reverse_arc":false,"high_magnitude":false,"override_rng_use_index":false,"strain_always":false,"show_effective_angles":true,"swimming_button":"A","track_moved_distance":false,"grind_divisor":8,"moved_distance":0,"atan_d":0,"dyaw":false,"moved_distance_axis":{"z":0,"y":0,"x":0},"override_rng_value":0,"strain_speed_target":false,"strain_left":true,"atan_exp":0,"lookahead":false,"atan_r":1,"moved_distance_ignore_y":false,"active_style_index":1,"grind":false,"goal_angle":0,"ghost_path":"C:\\Users\\austi\\Desktop\\mupen64\\1.1.0\\sm64expert\\sm64lua\\recording.ghost","format_angles_degrees":false,"goal_mag":127,"strain_right":false,"grind_left":true,"movement_mode":1,"format_decimal_points":4,"atan_n":10,"controller_index":1,"movement_modes":{"match_yaw":2,"reverse_angle":3,"disabled":1,"match_angle":4},"swim":false},{"override_rng":false,"atan_strain":false,"lookahead_length":1,"truncate_effective_angle":false,"variables":[{"visible":true,"identifier":"yaw_facing"},{"visible":true,"identifier":"yaw_intended"},{"visible":true,"identifier":"h_spd"},{"visible":true,"identifier":"v_spd"},{"visible":true,"identifier":"spd_efficiency"},{"visible":true,"identifier":"position_x"},{"visible":true,"identifier":"position_y"},{"visible":true,"identifier":"position_z"},{"visible":true,"identifier":"xz_movement"},{"visible":true,"identifier":"action"},{"visible":true,"identifier":"rng"},{"visible":true,"identifier":"moved_dist"},{"visible":true,"identifier":"atan_basic"},{"visible":true,"identifier":"atan_start_frame"}],"framewalk":false,"visualize_objects":false,"atan_start":0,"grid_gap":2,"grid_size":35,"reverse_arc":false,"high_magnitude":false,"override_rng_use_index":false,"strain_always":false,"show_effective_angles":true,"swimming_button":"A","track_moved_distance":false,"grind_divisor":8,"moved_distance":0,"atan_d":0,"dyaw":false,"moved_distance_axis":{"z":0,"y":0,"x":0},"override_rng_value":0,"strain_speed_target":false,"strain_left":true,"atan_exp":0,"lookahead":false,"atan_r":1,"moved_distance_ignore_y":false,"active_style_index":1,"grind":false,"goal_angle":0,"ghost_path":"C:\\Users\\austi\\Desktop\\mupen64\\1.1.0\\sm64expert\\sm64lua\\recording.ghost","format_angles_degrees":false,"goal_mag":127,"strain_right":false,"grind_left":true,"movement_mode":1,"format_decimal_points":4,"atan_n":10,"controller_index":1,"movement_modes":{"match_yaw":2,"reverse_angle":3,"disabled":1,"match_angle":4},"swim":false}],"protocol":1}